{
	"info": {
		"_postman_id": "a1b2c3d4-e5f6-7890-1234-567890abcdef",
		"name": "Examen Arquitectura - Microservicio Optimización",
		"schema": "https://schema.getpostman.com/json/collection/v2.1.0/collection.json"
	},
	"item": [
		{
			"name": "Caso de Éxito 1",
			"request": {
				"method": "POST",
				"header": [],
				"body": {
					"mode": "raw",
					"raw": "{\n    \"capacidad\": 10000,\n    \"objetos\": [\n        {\n            \"nombre\": \"Fondo_A\",\n            \"peso\": 2000,\n            \"ganancia\": 1500\n        },\n        {\n            \"nombre\": \"Fondo_B\",\n            \"peso\": 4000,\n            \"ganancia\": 3500\n        },\n        {\n            \"nombre\": \"Fondo_C\",\n            \"peso\": 5000,\n            \"ganancia\": 4000\n        },\n        {\n            \"nombre\": \"Fondo_D\",\n            \"peso\": 3000,\n            \"ganancia\": 2500\n        },\n        {\n            \"nombre\": \"Fondo_E\",\n            \"peso\": 1500,\n            \"ganancia\": 1800\n        }\n    ]\n}",
					"options": {
						"raw": {
							"language": "json"
						}
					}
				},
				"url": {
					"raw": "http://localhost:5000/optimizar",
					"protocol": "http",
					"host": [
						"localhost"
					],
					"port": "5000",
					"path": [
						"optimizar"
					]
				}
			},
			"response": []
		},
		{
			"name": "Caso de Éxito 2",
			"request": {
				"method": "POST",
				"header": [],
				"body": {
					"mode": "raw",
					"raw": "{\n    \"capacidad\": 8000,\n    \"objetos\": [\n        {\n            \"nombre\": \"Acción_X\",\n            \"peso\": 1000,\n            \"ganancia\": 800\n        },\n        {\n            \"nombre\": \"Acción_Y\",\n            \"peso\": 2500,\n            \"ganancia\": 2200\n        },\n        {\n            \"nombre\": \"Acción_Z\",\n            \"peso\": 3000,\n            \"ganancia\": 2800\n        },\n        {\n            \"nombre\": \"Bono_P\",\n            \"peso\": 4000,\n            \"ganancia\": 3000\n        },\n        {\n            \"nombre\": \"Bono_Q\",\n            \"peso\": 1500,\n            \"ganancia\": 1200\n        }\n    ]\n}",
					"options": {
						"raw": {
							"language": "json"
						}
					}
				},
				"url": {
					"raw": "http://localhost:5000/optimizar",
					"protocol": "http",
					"host": [
						"localhost"
					],
					"port": "5000",
					"path": [
						"optimizar"
					]
				}
			},
			"response": []
		},
		{
			"name": "Caso de Éxito 3",
			"request": {
				"method": "POST",
				"header": [],
				"body": {
					"mode": "raw",
					"raw": "{\n    \"capacidad\": 5000,\n    \"objetos\": [\n        {\n            \"nombre\": \"Cripto_1\",\n            \"peso\": 500,\n            \"ganancia\": 700\n        },\n        {\n            \"nombre\": \"Cripto_2\",\n            \"peso\": 800,\n            \"ganancia\": 1000\n        },\n        {\n            \"nombre\": \"ETF_1\",\n            \"peso\": 1500,\n            \"ganancia\": 1300\n        },\n        {\n            \"nombre\": \"ETF_2\",\n            \"peso\": 2000,\n            \"ganancia\": 1800\n        },\n        {\n            \"nombre\": \"NFT_Alpha\",\n            \"peso\": 3000,\n            \"ganancia\": 2500\n        }\n    ]\n}",
					"options": {
						"raw": {
							"language": "json"
						}
					}
				},
				"url": {
					"raw": "http://localhost:5000/optimizar",
					"protocol": "http",
					"host": [
						"localhost"
					],
					"port": "5000",
					"path": [
						"optimizar"
					]
				}
			},
			"response": []
		}
	]
}